Knapsack.py
Player.py
runKnap.py
KnapKingsTest2-0.0.1.dist-info/LICENSE.txt
KnapKingsTest2-0.0.1.dist-info/METADATA
KnapKingsTest2-0.0.1.dist-info/WHEEL
KnapKingsTest2-0.0.1.dist-info/top_level.txt
KnapKingsTest2-0.0.1.dist-info/RECORD
