Metadata-Version: 2.1
Name: KnapKingsTest2
Version: 0.0.1
Summary: Daily Fantasy Sports Optimization Package
Home-page: https://github.com/dylanmortimer12/KnapKings
Author: Greg Dray and Dylan Mortimer
Author-email: dmortimer@middlebury.edu
License: UNKNOWN
Platform: UNKNOWN
Classifier: Programming Language :: Python :: 3
Classifier: License :: OSI Approved :: MIT License
Classifier: Operating System :: OS Independent
Requires-Dist: numpy
Requires-Dist: beautifulsoup4
Requires-Dist: requests
Requires-Dist: csv
Requires-Dist: re
Requires-Dist: urllib
Requires-Dist: datetime
Requires-Dist: random
